pyramids/__init__.py
pyramids/_errors.py
pyramids/_io.py
pyramids/_utils.py
pyramids/abstract_dataset.py
pyramids/config.py
pyramids/config.yaml
pyramids/datacube.py
pyramids/dataset.py
pyramids/featurecollection.py
pyramids/gdal_drivers.yaml
pyramids/netcdf.py
pyramids/ogr_drivers.yaml
pyramids_gis-0.8.0.dist-info/licenses/AUTHORS.rst
pyramids_gis-0.8.0.dist-info/licenses/LICENSE.md
pyramids_gis-0.8.0.dist-info/METADATA
pyramids_gis-0.8.0.dist-info/WHEEL
pyramids_gis-0.8.0.dist-info/top_level.txt
pyramids_gis-0.8.0.dist-info/RECORD
