Metadata-Version: 2.4
Name: pyramids-gis
Version: 0.8.0
Summary: GIS utility package
Author-email: Mostafa Farrag <moah.farag@gmail.com>
License: GNU General Public License v3
Project-URL: homepage, https://github.com/Serapieum-of-alex/pyramids
Project-URL: repository, https://github.com/Serapieum-of-alex/pyramids
Project-URL: documentation, https://serapieum-of-alex.github.io/pyramids
Project-URL: Changelog, https://github.com/Serapieum-of-alex/pyramids/docs/change-log.md
Keywords: GIS,gdal
Classifier: Development Status :: 5 - Production/Stable
Classifier: Environment :: Console
Classifier: License :: OSI Approved :: GNU General Public License v3 (GPLv3)
Classifier: Natural Language :: English
Classifier: Programming Language :: Python :: 3
Classifier: Programming Language :: Python :: 3.11
Classifier: Programming Language :: Python :: 3.12
Classifier: Programming Language :: Python :: 3.13
Classifier: Topic :: Scientific/Engineering :: GIS
Classifier: Intended Audience :: Science/Research
Classifier: Intended Audience :: Developers
Requires-Python: <4,>=3.11
License-File: LICENSE.md
License-File: AUTHORS.rst
Requires-Dist: geopandas>=1.0.0
Requires-Dist: hpc-utils>=0.1.5
Requires-Dist: loguru>=0.7.2
Requires-Dist: numpy>=2.0.0
Requires-Dist: pandas>=2.0.0
Requires-Dist: pyproj>=3.7.0
Requires-Dist: PyYAML>=6.0.0
Requires-Dist: Shapely>=2.0.0
Provides-Extra: dev
Requires-Dist: nbval>=0.11.0; extra == "dev"
Requires-Dist: pre-commit>=3.7.1; extra == "dev"
Requires-Dist: pre-commit-hooks>=4.6.0; extra == "dev"
Requires-Dist: pytest>=8.2.2; extra == "dev"
Requires-Dist: pytest-cov>=5.0.0; extra == "dev"
Requires-Dist: coverage; extra == "dev"
Requires-Dist: build>=1.0.0; extra == "dev"
Requires-Dist: twine>=5.0.0; extra == "dev"
Requires-Dist: pip; extra == "dev"
Requires-Dist: jupyterlab; extra == "dev"
Requires-Dist: notebook; extra == "dev"
Requires-Dist: jupyter; extra == "dev"
Requires-Dist: commitizen>=4.8.4; extra == "dev"
Provides-Extra: docs
Requires-Dist: mkdocs>=1.5.3; extra == "docs"
Requires-Dist: mkdocs-material>=9.5.3; extra == "docs"
Requires-Dist: mkdocstrings>=0.24.0; extra == "docs"
Requires-Dist: mkdocstrings-python>=1.7.5; extra == "docs"
Requires-Dist: mike>=2.1.3; extra == "docs"
Requires-Dist: mkdocs-jupyter>=0.25.1; extra == "docs"
Requires-Dist: mkdocs-autorefs>=1.2; extra == "docs"
Requires-Dist: mkdocs-macros-plugin>=1.3.7; extra == "docs"
Requires-Dist: mkdocs-table-reader-plugin>=3.1.0; extra == "docs"
Requires-Dist: mkdocs-mermaid2-plugin>=1.2.1; extra == "docs"
Requires-Dist: jupyter-contrib-nbextensions>=0.7.0; extra == "docs"
Requires-Dist: mkdocs-panzoom-plugin; extra == "docs"
Requires-Dist: notebook<7.0; extra == "docs"
Provides-Extra: viz
Requires-Dist: cleopatra>=0.6.0; extra == "viz"
Dynamic: license-file
